arkitekt_server/__init__.py
arkitekt_server/config.py
arkitekt_server/dev.py
arkitekt_server/device_id.py
arkitekt_server/diff.py
arkitekt_server/logo.py
arkitekt_server/main.py
arkitekt_server/utils.py
arkitekt_server/wizard.py
arkitekt_server/commands/__init__.py
arkitekt_server/commands/auth.py
arkitekt_server/commands/build.py
arkitekt_server/commands/core.py
arkitekt_server/commands/init.py
arkitekt_server/commands/inspect.py
arkitekt_server/commands/organization.py
arkitekt_server/commands/service.py
arkitekt_server/commands/user.py
arkitekt_server/schemas/elektro_v1.graphql
arkitekt_server/schemas/fluss_v1.graphql
arkitekt_server/schemas/kabinet_v1.graphql
arkitekt_server/schemas/kraph_v1.graphql
arkitekt_server/schemas/mikro_v1.graphql
arkitekt_server/schemas/rekuest_v1.graphql
arkitekt_server-2.1.0.dist-info/METADATA
arkitekt_server-2.1.0.dist-info/WHEEL
arkitekt_server-2.1.0.dist-info/entry_points.txt
arkitekt_server-2.1.0.dist-info/RECORD
