Metadata-Version: 2.4
Name: arkitekt-server
Version: 2.1.0
Summary: Add your description here
Author-email: Your Name <your.email@example.com>
Keywords: arkitekt,server
Classifier: Development Status :: 4 - Beta
Classifier: License :: OSI Approved :: MIT License
Classifier: Operating System :: OS Independent
Classifier: Programming Language :: Python :: 3
Classifier: Programming Language :: Python :: 3.12
Requires-Python: >=3.11
Requires-Dist: click>=8.2.1
Requires-Dist: cryptography>=45.0.5
Requires-Dist: inquirer>=3.4.0
Requires-Dist: namegenerator>=1.0.6
Requires-Dist: platformdirs>=4.5.1
Requires-Dist: py-machineid>=1.0.0
Requires-Dist: pydantic>=2.11.7
Requires-Dist: python-slugify>=8.0.4
Requires-Dist: pyyaml>=6.0.2
Requires-Dist: rich-click>=1.8.9
Requires-Dist: typer>=0.16.0
